anisoms/__init__.py
anisoms/anisoms.py
anisoms/asc_to_csv.py
anisoms/params_from_asc.py
anisoms/plot.py
anisoms/print_ran_tensor.py
anisoms/tensor_to_dir.py
anisoms-1.0.0.dist-info/COPYING
anisoms-1.0.0.dist-info/METADATA
anisoms-1.0.0.dist-info/WHEEL
anisoms-1.0.0.dist-info/entry_points.txt
anisoms-1.0.0.dist-info/top_level.txt
anisoms-1.0.0.dist-info/RECORD
