Metadata-Version: 2.1
Name: anisoms
Version: 1.0.0
Summary: Read AMS (anisotropy of magnetic susceptibility) data
Home-page: https://github.com/pont-us/anisoms
Author: Pontus Lurcock
Author-email: pont@talvi.net
License: UNKNOWN
Platform: UNKNOWN
Classifier: License :: OSI Approved :: GNU General Public License v3 or later (GPLv3+)
Classifier: Programming Language :: Python :: 3
Requires-Dist: numpy
Requires-Dist: pyx
